{
  "categories": [
    {
      "name": "Our Dishes",
      "items": [
        { "name": "Shrimps Chips", "tag": "Exotic", "price": "€4", "desc": "", "image": "/placeholder.svg"},
        { "name": "Shrimp Tempura", "tag": "Popular", "price": "€10", "desc": "Crunchy Shrimps / 6pcs", "image": "/placeholder.svg" },
        { "name": "Bao - Bans Shrimps", "tag": "Exotic", "price": "€11.90", "desc": "Baobans bun • Spicy mayo • Cucumber • Avocado • Korean carrot • Microgreen peas • Sesame seeds • Srimp chips / 3pcs", "image": "/placeholder.svg" },
        { "name": "Spring rolls", "tag": "Premium", "price": "€8", "desc": "Spring rolls Kim Chi / Spring rolls Vega / 5pcs + Spring rolls sauce", "image": "/placeholder.svg" },
        { "name": "Gyoza", "tag": "Exotic", "price": "€10", "desc": "Shrimp / Chicken / Pork Kim-Chi Gyoza 6pcs • Spicy sauce • Gyoza Sauce • Sesame • Green onion", "image": "/placeholder.svg"}
      ]
    }
  ]
}